[
  {
    "ccn": "145222",
    "name": "La Bella of Woodstock",
    "address": "309 MCHENRY AVENUE",
    "city": "WOODSTOCK",
    "state": "IL",
    "zip": "60098",
    "phone": "8153381700",
    "county": "Mc Henry",
    "ownershipType": "For profit - Individual",
    "certifiedBeds": "115",
    "avgResidentsPerDay": "67.5",
    "isCcrc": "N",
    "specialFocusStatus": null,
    "abuseIcon": "Y",
    "overallRating": "1",
    "healthInspectionRating": "1",
    "qmRating": "4",
    "staffingRating": "1",
    "reportedTotalNurseStaffingHrsPerResidentDay": "3.04964",
    "totalNumberHealthDeficiencies_cycle1": "30",
    "numberOfFines": "6",
    "totalFinesDollars": "455016.00",
    "numberOfPaymentDenials": "3",
    "totalNumberOfPenalties": "9",
    "latitude": "42.3194",
    "longitude": "-88.443",
    "processingDate": "2026-06-01"
  },
  {
    "ccn": "145257",
    "name": "CRYSTAL PINES REHAB & HCC",
    "address": "335 NORTH ILLINOIS AVENUE",
    "city": "CRYSTAL LAKE",
    "state": "IL",
    "zip": "60014",
    "phone": "8154597791",
    "county": "Mc Henry",
    "ownershipType": "For profit - Corporation",
    "certifiedBeds": "110",
    "avgResidentsPerDay": "81.2",
    "isCcrc": "N",
    "specialFocusStatus": null,
    "abuseIcon": "Y",
    "overallRating": "1",
    "healthInspectionRating": "2",
    "qmRating": "2",
    "staffingRating": "1",
    "reportedTotalNurseStaffingHrsPerResidentDay": "3.14603",
    "totalNumberHealthDeficiencies_cycle1": "16",
    "numberOfFines": "3",
    "totalFinesDollars": "52795.00",
    "numberOfPaymentDenials": "1",
    "totalNumberOfPenalties": "4",
    "latitude": "42.2335",
    "longitude": "-88.369",
    "processingDate": "2026-06-01"
  },
  {
    "ccn": "145453",
    "name": "ALDEN TERRACE OF MCHENRY REHAB",
    "address": "803 ROYAL DRIVE",
    "city": "MCHENRY",
    "state": "IL",
    "zip": "60050",
    "phone": "8153442600",
    "county": "Mc Henry",
    "ownershipType": "For profit - Corporation",
    "certifiedBeds": "316",
    "avgResidentsPerDay": "158.9",
    "isCcrc": "N",
    "specialFocusStatus": null,
    "abuseIcon": "N",
    "overallRating": "2",
    "healthInspectionRating": "3",
    "qmRating": "4",
    "staffingRating": "1",
    "reportedTotalNurseStaffingHrsPerResidentDay": "2.88553",
    "totalNumberHealthDeficiencies_cycle1": "25",
    "numberOfFines": "1",
    "totalFinesDollars": "11170.00",
    "numberOfPaymentDenials": "0",
    "totalNumberOfPenalties": "1",
    "latitude": "42.3381",
    "longitude": "-88.287",
    "processingDate": "2026-06-01"
  },
  {
    "ccn": "145612",
    "name": "PEARL OF CRYSTAL LAKE, THE",
    "address": "1000 EAST BRIGHTON LANE",
    "city": "CRYSTAL LAKE",
    "state": "IL",
    "zip": "60012",
    "phone": "8154776569",
    "county": "Mc Henry",
    "ownershipType": "For profit - Corporation",
    "certifiedBeds": "97",
    "avgResidentsPerDay": "70.9",
    "isCcrc": "N",
    "specialFocusStatus": null,
    "abuseIcon": "N",
    "overallRating": "5",
    "healthInspectionRating": "4",
    "qmRating": "5",
    "staffingRating": "4",
    "reportedTotalNurseStaffingHrsPerResidentDay": "3.88218",
    "totalNumberHealthDeficiencies_cycle1": "7",
    "numberOfFines": "0",
    "totalFinesDollars": "0.00",
    "numberOfPaymentDenials": "0",
    "totalNumberOfPenalties": "0",
    "latitude": "42.2678",
    "longitude": "-88.284",
    "processingDate": "2026-06-01"
  },
  {
    "ccn": "145652",
    "name": "VALLEY HI NURSING HOME",
    "address": "2406 HARTLAND ROAD",
    "city": "WOODSTOCK",
    "state": "IL",
    "zip": "60098",
    "phone": "8153380312",
    "county": "Mc Henry",
    "ownershipType": "Government - County",
    "certifiedBeds": "128",
    "avgResidentsPerDay": "102.6",
    "isCcrc": "N",
    "specialFocusStatus": null,
    "abuseIcon": "N",
    "overallRating": "3",
    "healthInspectionRating": "2",
    "qmRating": "3",
    "staffingRating": "5",
    "reportedTotalNurseStaffingHrsPerResidentDay": "4.44410",
    "totalNumberHealthDeficiencies_cycle1": "15",
    "numberOfFines": "3",
    "totalFinesDollars": "155366.00",
    "numberOfPaymentDenials": "2",
    "totalNumberOfPenalties": "5",
    "latitude": "42.3614",
    "longitude": "-88.511",
    "processingDate": "2026-06-01"
  },
  {
    "ccn": "145917",
    "name": "FAIR OAKS HEALTH CARE CENTER",
    "address": "471 TERRA COTTA AVENUE",
    "city": "CRYSTAL LAKE",
    "state": "IL",
    "zip": "60014",
    "phone": "8154550550",
    "county": "Mc Henry",
    "ownershipType": "Non profit - Corporation",
    "certifiedBeds": "51",
    "avgResidentsPerDay": "40.4",
    "isCcrc": "N",
    "specialFocusStatus": null,
    "abuseIcon": "N",
    "overallRating": "3",
    "healthInspectionRating": "3",
    "qmRating": "3",
    "staffingRating": "4",
    "reportedTotalNurseStaffingHrsPerResidentDay": "5.06602",
    "totalNumberHealthDeficiencies_cycle1": "10",
    "numberOfFines": "2",
    "totalFinesDollars": "31230.00",
    "numberOfPaymentDenials": "1",
    "totalNumberOfPenalties": "3",
    "latitude": "42.248",
    "longitude": "-88.339",
    "processingDate": "2026-06-01"
  },
  {
    "ccn": "146014",
    "name": "MERCY HARVARD HOSPITAL CARE CENTER",
    "address": "901 SOUTH GRANT",
    "city": "HARVARD",
    "state": "IL",
    "zip": "60033",
    "phone": "8159432967",
    "county": "Mc Henry",
    "ownershipType": "Non profit - Corporation",
    "certifiedBeds": "34",
    "avgResidentsPerDay": "19.0",
    "isCcrc": "N",
    "specialFocusStatus": null,
    "abuseIcon": "N",
    "overallRating": "5",
    "healthInspectionRating": "5",
    "qmRating": "3",
    "staffingRating": "5",
    "reportedTotalNurseStaffingHrsPerResidentDay": "6.03212",
    "totalNumberHealthDeficiencies_cycle1": "3",
    "numberOfFines": "0",
    "totalFinesDollars": "0.00",
    "numberOfPaymentDenials": "0",
    "totalNumberOfPenalties": "0",
    "latitude": "42.4146",
    "longitude": "-88.667",
    "processingDate": "2026-06-01"
  },
  {
    "ccn": "146127",
    "name": "FLORENCE NURSING HOME",
    "address": "546 EAST GRANT HIGHWAY",
    "city": "MARENGO",
    "state": "IL",
    "zip": "60152",
    "phone": "8155688322",
    "county": "Mc Henry",
    "ownershipType": "For profit - Limited Liability company",
    "certifiedBeds": "56",
    "avgResidentsPerDay": "35.7",
    "isCcrc": "N",
    "specialFocusStatus": null,
    "abuseIcon": "N",
    "overallRating": "5",
    "healthInspectionRating": "5",
    "qmRating": "3",
    "staffingRating": "2",
    "reportedTotalNurseStaffingHrsPerResidentDay": "3.16058",
    "totalNumberHealthDeficiencies_cycle1": "2",
    "numberOfFines": "0",
    "totalFinesDollars": "0.00",
    "numberOfPaymentDenials": "1",
    "totalNumberOfPenalties": "1",
    "latitude": "42.2464",
    "longitude": "-88.602",
    "processingDate": "2026-06-01"
  },
  {
    "ccn": "146186",
    "name": "ALDEN ESTATES CTS OF HUNTLEY",
    "address": "12140 REGENCY PARKWAY",
    "city": "HUNTLEY",
    "state": "IL",
    "zip": "60142",
    "phone": "8479617500",
    "county": "Mc Henry",
    "ownershipType": "For profit - Corporation",
    "certifiedBeds": "170",
    "avgResidentsPerDay": "141.7",
    "isCcrc": "N",
    "specialFocusStatus": null,
    "abuseIcon": "N",
    "overallRating": "2",
    "healthInspectionRating": "2",
    "qmRating": "4",
    "staffingRating": "2",
    "reportedTotalNurseStaffingHrsPerResidentDay": "3.58809",
    "totalNumberHealthDeficiencies_cycle1": "10",
    "numberOfFines": "3",
    "totalFinesDollars": "183372.00",
    "numberOfPaymentDenials": "0",
    "totalNumberOfPenalties": "3",
    "latitude": "42.1485",
    "longitude": "-88.437",
    "processingDate": "2026-06-01"
  },
  {
    "ccn": "146195",
    "name": "IGNITE MEDICAL MCHENRY",
    "address": "550 RIDGEVIEW DRIVE",
    "city": "MCHENRY",
    "state": "IL",
    "zip": "60050",
    "phone": "8159002500",
    "county": "Mc Henry",
    "ownershipType": "For profit - Limited Liability company",
    "certifiedBeds": "84",
    "avgResidentsPerDay": "81.1",
    "isCcrc": "N",
    "specialFocusStatus": null,
    "abuseIcon": "N",
    "overallRating": "4",
    "healthInspectionRating": "3",
    "qmRating": "5",
    "staffingRating": "3",
    "reportedTotalNurseStaffingHrsPerResidentDay": "3.43185",
    "totalNumberHealthDeficiencies_cycle1": "12",
    "numberOfFines": "1",
    "totalFinesDollars": "62153.00",
    "numberOfPaymentDenials": "0",
    "totalNumberOfPenalties": "1",
    "latitude": "42.3203",
    "longitude": "-88.286",
    "processingDate": "2026-06-01"
  }
]